diehard/__init__.py
diehard/overlapping_permutations.py
diehard-0.0.1.dist-info/DESCRIPTION.rst
diehard-0.0.1.dist-info/METADATA
diehard-0.0.1.dist-info/RECORD
diehard-0.0.1.dist-info/WHEEL
diehard-0.0.1.dist-info/metadata.json
diehard-0.0.1.dist-info/top_level.txt
