Metadata-Version: 2.0
Name: diehard
Version: 0.0.1
Summary: Tests for randomness.
Home-page: http://diehard.readthedocs.io/en/latest/
Author: Elton Law
Author-email: eltonlaw296@gmail.com
License: Apache License 2.0
Download-URL: https://github.com/eltonlaw/diehard
Keywords: rng,tests
Platform: UNKNOWN
Classifier: Development Status :: 3 - Alpha
Classifier: Intended Audience :: Science/Research
Classifier: Intended Audience :: Developers
Classifier: Programming Language :: Python
Classifier: Topic :: Software Development
Classifier: Topic :: Scientific/Engineering
Requires-Dist: numpy (==1.14.1)
Provides-Extra: dev
Requires-Dist: pylint; extra == 'dev'
Requires-Dist: sphinx; extra == 'dev'
Provides-Extra: test
Requires-Dist: tox; extra == 'test'
